{
    "lang": "astu",
    "year": 2021,
    "month": 11,
    "day": 17,
    "title": "17 de payares de 2015",
    "body": " Un total de 195 estaos ratificaron la creaci\u00f3n de los Xeoparques Mundiales de la UNESCO. Son llugares con un patrimoniu xeol\u00f3xicu de relevancia internacional que s\u2019empleguen pa promover el desendolcu sostenible de les comunidaes qu\u2019habiten nellos",
    "eventYear": "2015",
    "image": "https://calendario-cientifico-escolar.github.io/images/personajes/321.png"
}